{
	"configurations" : 
	[
		{
			"abstractTargets" : [],
			"directories" : 
			[
				{
					"build" : ".",
					"jsonFile" : "directory-.-Debug-f6f22219c74102c3da70.json",
					"minimumCMakeVersion" : 
					{
						"string" : "3.15"
					},
					"projectIndex" : 0,
					"source" : ".",
					"targetIndexes" : 
					[
						0
					]
				}
			],
			"name" : "Debug",
			"projects" : 
			[
				{
					"directoryIndexes" : 
					[
						0
					],
					"name" : "PlaneWar",
					"targetIndexes" : 
					[
						0
					]
				}
			],
			"targets" : 
			[
				{
					"directoryIndex" : 0,
					"id" : "PlaneWar::@6890427a1f51a3e7e1df",
					"jsonFile" : "target-PlaneWar-Debug-a0a6d5abc57f2d1e0185.json",
					"name" : "PlaneWar",
					"projectIndex" : 0
				}
			]
		}
	],
	"kind" : "codemodel",
	"paths" : 
	{
		"build" : "D:/\u98de\u673a\u5927\u6218/\u98de\u673a\u5927\u6218/out/build/x64-Debug",
		"source" : "D:/\u98de\u673a\u5927\u6218/\u98de\u673a\u5927\u6218"
	},
	"version" : 
	{
		"major" : 2,
		"minor" : 9
	}
}
